_muFFT.cpython-310-aarch64-linux-gnu.so
_muGrid.cpython-310-aarch64-linux-gnu.so
.mufft.mesonpy.libs/libmuFFT.so
.mufft.mesonpy.libs/libmuGrid.so
.mufft.mesonpy.libs/pkgconfig/eigen3.pc
mufft-0.95.0.data/headers/eigen3/signature_of_eigen3_matrix_library
mufft-0.95.0.data/headers/eigen3/Eigen/Cholesky
mufft-0.95.0.data/headers/eigen3/Eigen/CholmodSupport
mufft-0.95.0.data/headers/eigen3/Eigen/Core
mufft-0.95.0.data/headers/eigen3/Eigen/Dense
mufft-0.95.0.data/headers/eigen3/Eigen/Eigen
mufft-0.95.0.data/headers/eigen3/Eigen/Eigenvalues
mufft-0.95.0.data/headers/eigen3/Eigen/Geometry
mufft-0.95.0.data/headers/eigen3/Eigen/Householder
mufft-0.95.0.data/headers/eigen3/Eigen/IterativeLinearSolvers
mufft-0.95.0.data/headers/eigen3/Eigen/Jacobi
mufft-0.95.0.data/headers/eigen3/Eigen/KLUSupport
mufft-0.95.0.data/headers/eigen3/Eigen/LU
mufft-0.95.0.data/headers/eigen3/Eigen/MetisSupport
mufft-0.95.0.data/headers/eigen3/Eigen/OrderingMethods
mufft-0.95.0.data/headers/eigen3/Eigen/PaStiXSupport
mufft-0.95.0.data/headers/eigen3/Eigen/PardisoSupport
mufft-0.95.0.data/headers/eigen3/Eigen/QR
mufft-0.95.0.data/headers/eigen3/Eigen/QtAlignedMalloc
mufft-0.95.0.data/headers/eigen3/Eigen/SPQRSupport
mufft-0.95.0.data/headers/eigen3/Eigen/SVD
mufft-0.95.0.data/headers/eigen3/Eigen/Sparse
mufft-0.95.0.data/headers/eigen3/Eigen/SparseCholesky
mufft-0.95.0.data/headers/eigen3/Eigen/SparseCore
mufft-0.95.0.data/headers/eigen3/Eigen/SparseLU
mufft-0.95.0.data/headers/eigen3/Eigen/SparseQR
mufft-0.95.0.data/headers/eigen3/Eigen/StdDeque
mufft-0.95.0.data/headers/eigen3/Eigen/StdList
mufft-0.95.0.data/headers/eigen3/Eigen/StdVector
mufft-0.95.0.data/headers/eigen3/Eigen/SuperLUSupport
mufft-0.95.0.data/headers/eigen3/Eigen/UmfPackSupport
mufft-0.95.0.data/headers/eigen3/Eigen/src/Cholesky/LDLT.h
mufft-0.95.0.data/headers/eigen3/Eigen/src/Cholesky/LLT.h
mufft-0.95.0.data/headers/eigen3/Eigen/src/Cholesky/LLT_LAPACKE.h
mufft-0.95.0.dist-info/LICENSE
mufft-0.95.0.dist-info/METADATA
mufft-0.95.0.dist-info/WHEEL
mufft-0.95.0.dist-info/RECORD
