Metadata-Version: 2.1
Name: muFFT
Version: 0.95.0
Summary: Unified interface to MPI-parallel FFT libraries
Author-Email: Lars Pastewka <lars.pastewka@imtek.uni-freiburg.de>, Ali Falsafi <ali.falsafi@epfl.ch>, Till Junge <till.junge@altermail.ch>, Richard Leute <richard.leute@imtek.uni-freiburg.de>
License:                    GNU LESSER GENERAL PUBLIC LICENSE
Classifier: Development Status :: 5 - Production/Stable
Classifier: Programming Language :: Python
Project-URL: documentation, https://muspectre.github.io/muFFT/
Project-URL: repository, https://github.com/muSpectre/muFFT
Project-URL: changelog, https://github.com/muSpectre/muFFT/blob/main/CHANGELOG.md
Requires-Python: >=3.9.0
Requires-Dist: muGrid>=0.95.0
Requires-Dist: numpy
Provides-Extra: test
Requires-Dist: pytest; extra == "test"
Requires-Dist: pytest-cov; extra == "test"
Requires-Dist: NuMPI; extra == "test"
